nettoolkit_common/__init__.py
nettoolkit_common/common.py
nettoolkit_common/gpl.py
nettoolkit_common-0.0.3.dist-info/LICENSE
nettoolkit_common-0.0.3.dist-info/METADATA
nettoolkit_common-0.0.3.dist-info/WHEEL
nettoolkit_common-0.0.3.dist-info/top_level.txt
nettoolkit_common-0.0.3.dist-info/RECORD
