Metadata-Version: 2.1
Name: nettoolkit-common
Version: 0.0.3
Summary: Networking Toolkit common Functions
Home-page: https://github.com/aliasgar1978/nettoolkit_common
Author: ALIASGAR - ALI
Author-email: aholo2000@gmail.com
Classifier: Programming Language :: Python :: 3
Classifier: License :: OSI Approved :: MIT License
Classifier: Operating System :: OS Independent
Requires-Python: >=3.8
License-File: LICENSE
Requires-Dist: pandas
